README.md
setup.py
gaiasdk/__init__.py
gaiasdk/job.py
gaiasdk/plugin_pb2.py
gaiasdk/plugin_pb2_grpc.py
gaiasdk/sdk.py
gaiasdk.egg-info/PKG-INFO
gaiasdk.egg-info/SOURCES.txt
gaiasdk.egg-info/dependency_links.txt
gaiasdk.egg-info/not-zip-safe
gaiasdk.egg-info/requires.txt
gaiasdk.egg-info/top_level.txt